dbt/adapters/spark/__init__.py
dbt/adapters/spark/__version__.py
dbt/adapters/spark/column.py
dbt/adapters/spark/connections.py
dbt/adapters/spark/impl.py
dbt/adapters/spark/relation.py
dbt/include/spark/__init__.py
dbt/include/spark/dbt_project.yml
dbt/include/spark/profile_template.yml
dbt/include/spark/macros/adapters.sql
dbt/include/spark/macros/materializations/seed.sql
dbt/include/spark/macros/materializations/snapshot.sql
dbt/include/spark/macros/materializations/table.sql
dbt/include/spark/macros/materializations/view.sql
dbt/include/spark/macros/materializations/incremental/incremental.sql
dbt/include/spark/macros/materializations/incremental/strategies.sql
dbt/include/spark/macros/materializations/incremental/validate.sql
slickdeals_dbt_spark-1.0.1.dist-info/METADATA
slickdeals_dbt_spark-1.0.1.dist-info/WHEEL
slickdeals_dbt_spark-1.0.1.dist-info/top_level.txt
slickdeals_dbt_spark-1.0.1.dist-info/RECORD
