Metadata-Version: 2.1
Name: slickdeals-dbt-spark
Version: 1.0.1
Summary: The Apache Spark adapter plugin for dbt, slickdeals flavor
Home-page: https://github.com/ryanClift-sd/dbt-spark
Author: dbt Labs
Author-email: ryan.clift@slickdeals.net
License: UNKNOWN
Platform: UNKNOWN
Classifier: Development Status :: 5 - Production/Stable
Classifier: License :: OSI Approved :: Apache Software License
Classifier: Operating System :: Microsoft :: Windows
Classifier: Operating System :: MacOS :: MacOS X
Classifier: Operating System :: POSIX :: Linux
Classifier: Programming Language :: Python :: 3.7
Classifier: Programming Language :: Python :: 3.8
Classifier: Programming Language :: Python :: 3.9
Requires-Python: >=3.7
Requires-Dist: dbt-core (~=1.0.0)
Requires-Dist: sqlparams (>=3.0.0)
Provides-Extra: odbc
Requires-Dist: pyodbc (>=4.0.30) ; extra == 'odbc'
Provides-Extra: pyhive
Requires-Dist: PyHive[hive] (<0.7.0,>=0.6.0) ; extra == 'pyhive'
Requires-Dist: thrift (<0.16.0,>=0.11.0) ; extra == 'pyhive'
Provides-Extra: all
Requires-Dist: PyHive[hive] (<0.7.0,>=0.6.0) ; extra == 'all'
Requires-Dist: pyodbc (>=4.0.30) ; extra == 'all'
Requires-Dist: thrift (<0.16.0,>=0.11.0) ; extra == 'all'
